[
  {
    "id": "path-of-exile",
    "name": {
      "en": "Path of Exile 1",
      "ru": "Path of Exile 1"
    },
    "adapter": "PoEAdapter",
    "enabled": true,
    "sourceUrl": "https://www.pathofexile.com/news/rss"
  },
  {
    "id": "path-of-exile-2",
    "name": {
      "en": "Path of Exile 2",
      "ru": "Path of Exile 2"
    },
    "adapter": "StaticAdapter",
    "enabled": true,
    "staticData": {
      "developer": "Grinding Gear Games",
      "logo": "path-of-exile-2.png",
      "color": "#4b6e9c",
      "icon": "✨",
      "website": "https://pathofexile2.com",
      "latestNews": {
        "title": "Path of Exile 2 Early Access FAQ & Info",
        "url": "https://www.pathofexile.com/forum/view-thread/3587981",
        "publishDate": "2026-05-29",
        "source": "Official FAQ"
      },
      "status": {
        "code": "early-access",
        "label": {
          "en": "Early Access",
          "ru": "Ранний доступ"
        }
      },
      "currentSeason": {
        "name": {
          "en": "0.5.0: Return of the Ancients",
          "ru": "0.5.0: Return of the Ancients"
        },
        "startDate": "2026-05-29",
        "endDate": "",
        "verification": "official",
        "sourceUrl": "https://www.pathofexile.com/forum/view-thread/3587981"
      },
      "nextSeason": {
        "name": {
          "en": "Version 1.0 (Release)",
          "ru": "Version 1.0 (Release)"
        },
        "startDate": "2026-12-15",
        "endDate": "",
        "verification": "official",
        "sourceUrl": "https://www.pathofexile.com/forum/view-thread/3587981"
      },
      "features": {
        "en": [
          "Runes of Aldur league testing",
          "Atlas of Worlds rework for the sequel",
          "New passive skill tree for early access",
          "Full release and new campaign acts in December"
        ],
        "ru": [
          "Тестирование лиги Runes of Aldur",
          "Переработка механики Атласа Миров под сиквел",
          "Новое древо пассивных умений для раннего доступа",
          "Полный релиз и новые акты кампании в декабре"
        ]
      }
    }
  },
  {
    "id": "diablo-iv",
    "name": {
      "en": "Diablo IV",
      "ru": "Diablo IV"
    },
    "adapter": "DiabloAdapter",
    "enabled": true,
    "sourceUrl": "https://news.blizzard.com/en-us/diablo4"
  },
  {
    "id": "last-epoch",
    "name": {
      "en": "Last Epoch",
      "ru": "Last Epoch"
    },
    "adapter": "LastEpochAdapter",
    "enabled": true,
    "appId": 899770
  },
  {
    "id": "torchlight-infinite",
    "name": {
      "en": "Torchlight: Infinite",
      "ru": "Торчлайт: Инфинит"
    },
    "adapter": "TorchlightAdapter",
    "enabled": true,
    "appId": 1974050
  }
]